netcdf2vtu/__init__.py
netcdf2vtu/cli.py
netcdf2vtu/netcdf2vtu.py
netcdf2vtu-0.1.1.dist-info/AUTHORS.md
netcdf2vtu-0.1.1.dist-info/LICENSE
netcdf2vtu-0.1.1.dist-info/METADATA
netcdf2vtu-0.1.1.dist-info/WHEEL
netcdf2vtu-0.1.1.dist-info/entry_points.txt
netcdf2vtu-0.1.1.dist-info/top_level.txt
netcdf2vtu-0.1.1.dist-info/RECORD
