Metadata-Version: 2.1
Name: netcdf2vtu
Version: 0.1.1
Summary: Mapping data from netCDF files on VTU.
Author-email: Johannes Boog <johannesboog@yahoo.de>
Project-URL: Homepage, https://gitlab.com/joboog/netcdf2vtu
Classifier: Intended Audience :: Science/Research
Classifier: Programming Language :: Python :: 3
Classifier: License :: OSI Approved :: BSD License
Classifier: Operating System :: Unix
Requires-Python: >=3.9
License-File: LICENSE
License-File: AUTHORS.md
Requires-Dist: netCDF4 (>=1.5.7)
Requires-Dist: numpy (>=1.22.3)
Requires-Dist: pyproj (>=3.4.1)
Requires-Dist: vtk (>=9.0.3)
